brainfuckpy/__init__.py
brainfuckpy/__main__.py
brainfuckpy/brainfuck.py
brainfuckpy/visualize.py
brainfuckpy-0.2.2.dist-info/LICENSE
brainfuckpy-0.2.2.dist-info/METADATA
brainfuckpy-0.2.2.dist-info/WHEEL
brainfuckpy-0.2.2.dist-info/top_level.txt
brainfuckpy-0.2.2.dist-info/RECORD
