Metadata-Version: 2.1
Name: brainfuckpy
Version: 0.2.2
Summary: A lightweight pure python brainfuck interpreter and visualizer
Author-email: Daan Olivier Koning <daanolivierkoning@gmail.com>
Project-URL: Homepage, https://github.com/daankoning/brainfuck.py
Keywords: pure python,brainfuck,interpeter,visualizer
Classifier: Programming Language :: Python :: 3
Classifier: License :: OSI Approved :: MIT License
Classifier: Operating System :: OS Independent
Requires-Python: >=3.9
License-File: LICENSE
